[1,["95nvgm3N5LZIDqtJyXxvSK@f9941","ccqaJzDQhP9LiDOOOepUWh","72glUUf1lN87uzlOZlvh8T@f9941","21sGZEAx5PaoaOAoEC7EkO@6c48a","b9HU85UllMTZTImR4xnOov@f9941","f2eZExpwdCZ6zAX0z8tDeN@f9941","87TfFnKWNMspmMIRNAIYf0@f9941","72glUUf1lN87uzlOZlvh8T@6c48a","87TfFnKWNMspmMIRNAIYf0@6c48a","21sGZEAx5PaoaOAoEC7EkO@f9941","c1Q3it/t9PK6v6wM6+ZUne@f9941","f2eZExpwdCZ6zAX0z8tDeN@6c48a"],["node","_spriteFrame","_textureSource","_cameraComponent","listComp","scene","_parent","_normalSprite","prefab","leftBubble","rightBubble","cellPrefab","root","contentNode","headNode","bubbleSprite","headIconSprite","textLabel","data"],[["cc.Node",["_name","_layer","_id","_components","_children","_parent","_prefab","_lpos","_lscale"],0,9,2,1,4,5,5],["cc.Widget",["_alignFlags","_top","_originalWidth","_originalHeight","_bottom","_left","_right","_alignMode","node","__prefab"],-5,1,4],["cc.Sprite",["_sizeMode","_type","node","_spriteFrame","__prefab","_color"],1,1,6,4,5],"cc.SpriteFrame",["cc.Node",["_name","_layer","_parent","_components","_prefab","_lpos"],1,1,12,4,5],["cc.UITransform",["node","_contentSize","__prefab"],3,1,5,4],["cc.Label",["_actualFontSize","_fontSize","_string","_horizontalAlign","_overflow","node","__prefab"],-2,1,4],["cc.SceneAsset",["_name"],2],["cc.Node",["_name","_parent","_components","_lpos"],2,1,2,5],["cc.Canvas",["node","_cameraComponent"],3,1,1],["793d5EHdv5KqoUNqnGn6QA2",["node","listComp","leftBubble","rightBubble","cellPrefab"],3,1,1,6,6,6],["cc.Layout",["_resizeMode","_layoutType","_spacingX","node"],0,1],["cc.Button",["node","clickEvents","_normalSprite"],3,1,9,6],["cc.ClickEvent",["_componentId","handler","target"],1,1],["cc.LabelOutline",["_width","node"],2,1],["cc.Scene",["_name","_children","_prefab","_globals"],2,2,4,4],["cc.PrefabInfo",["root","asset","fileId","instance","targetOverrides","nestedPrefabInstanceRoots"],-3],["cc.PrefabInfo",["fileId","instance","targetOverrides","nestedPrefabInstanceRoots","root","asset"],-1,1,1],["cc.SceneGlobals",["ambient","shadows","_skybox","fog","octree","skin","lightProbeInfo"],3,4,4,4,4,4,4,4],["cc.AmbientInfo",["_skyColorHDR","_groundAlbedoHDR"],3,5,5],["cc.ShadowsInfo",["_shadowColor","_size"],3,5,5],["cc.SkyboxInfo",[],3],["cc.FogInfo",[],3],["cc.OctreeInfo",[],3],["cc.SkinInfo",["_enabled"],2],["cc.LightProbeInfo",[],3],["cc.Camera",["_projection","_orthoHeight","_near","_visibility","node","_color"],-1,1,5],["f2c14q0UedOp7pnWIKia8C+",["preloadNodesLimitPerFrame","node","registerCellForEditor"],2,1,9],["_yx_editor_register_cell_info",["identifier","prefab"],2,6],["cc.Prefab",["_name"],2],["cc.CompPrefabInfo",["fileId"],2],["409e4pl4hpHk5dwiC0nhyJm",["node","__prefab","textLabel","headIconSprite","bubbleSprite","headNode","contentNode"],3,1,4,1,1,1,1,1]],[[30,0,2],[5,0,1,1],[17,0,1,2,3,4,5,5],[5,0,2,1,1],[0,0,1,5,3,3],[0,0,1,5,4,3,7,3],[4,0,1,2,3,4,3],[1,0,5,6,1,4,2,3,8,8],[1,0,2,3,8,4],[2,2,3,1],[6,2,0,1,5,4],[14,0,1,2],[7,0,2],[0,0,1,2,4,3,7,4],[0,0,1,5,4,3,3],[0,0,1,4,3,6,3],[0,0,1,5,4,3,6,3],[0,0,1,5,4,3,6,7,3],[0,0,1,5,4,3,6,8,3],[0,0,1,5,3,6,3],[4,0,1,2,3,3],[4,0,1,2,3,4,5,3],[8,0,1,2,3,2],[5,0,2,1],[9,0,1,1],[1,0,1,4,8,4],[1,0,5,1,8,4],[1,0,6,1,8,4],[1,0,2,3,7,8,9,5],[10,0,1,2,3,4,1],[2,0,2,3,2],[2,1,0,2,3,3],[2,2,4,3,1],[2,1,0,2,4,5,3],[2,2,4,1],[11,0,1,2,3,4],[12,0,1,2,1],[13,0,1,2,3],[6,3,0,1,4,5,6,5],[15,0,1,2,3,2],[16,0,1,2,3,4,5,7],[18,0,1,2,3,4,5,6,1],[19,0,1,1],[20,0,1,1],[21,1],[22,1],[23,1],[24,0,2],[25,1],[26,0,1,2,3,4,5,5],[27,0,1,2,2],[28,0,1,2],[29,0,2],[31,0,1,2,3,4,5,6,1]],[[[{"name":"color","rect":{"x":0,"y":0,"width":106,"height":106},"offset":{"x":0,"y":0},"originalSize":{"width":106,"height":106},"rotated":false,"capInsets":[20,20,20,20],"vertices":{"rawPosition":[-53,-53,0,53,-53,0,-53,53,0,53,53,0],"indexes":[0,1,2,2,1,3],"uv":[0,106,106,106,0,0,106,0],"nuv":[0,0,1,0,0,1,1,1],"minPos":{"x":-53,"y":-53,"z":0},"maxPos":{"x":53,"y":53,"z":0}},"packable":true,"pixelsToUnit":100,"pivot":{"x":0.5,"y":0.5},"meshType":0}],[3],0,[0],[2],[3]],[[[12,"demo10"],[13,"Canvas",33554432,"beI88Z2HpFELqR4T5EMHpg",[-7,-8,-9,-10,-11],[[1,-1,[5,720,1280]],[24,-3,-2],[25,45,5.684341886080802e-14,5.684341886080802e-14,-4],[29,-6,-5,6,7,8]],[1,360,640,0]],[5,"back",33554432,1,[-15],[[1,-12,[5,150,54]],[9,-13,1],[26,9,20,20,-14]],[1,-265,593,0]],[5,"menus",33554432,1,[-19],[[1,-16,[5,150,54]],[35,1,1,10,-17],[27,33,20,20,-18]],[1,265,593,0]],[14,"add",33554432,3,[-23],[[1,-20,[5,150,54]],[9,-21,2],[36,-22,[[37,"793d5EHdv5KqoUNqnGn6QA2","randomNewMessage",1]],3]]],[5,"chat",33554432,1,[-26,-27],[[1,-24,[5,600,1136]],[7,5,10,10,100,44,100,100,-25]],[1,0,-28,0]],[4,"bg",33554432,1,[[1,-28,[5,720,1280]],[8,45,100,100,-29],[30,0,-30,0]]],[4,"label",33554432,2,[[1,-31,[5,68,58.4]],[10,"返回",30,30,-32],[11,4,-33]]],[4,"label",33554432,4,[[1,-34,[5,128,58.4]],[10,"随机添加",30,30,-35],[11,4,-36]]],[4,"bg",33554432,5,[[1,-37,[5,600,1136]],[31,1,0,-38,4],[8,45,100,100,-39]]],[20,"list",33554432,5,[[[1,-40,[5,560,1048]],[7,45,20,20,44,44,100,100,-41],-42],4,4,1]],[39,"demo10",[1],[40,null,null,"e0d7a60b-4b6b-4ecc-8172-91837ea13bdb",null,null,null],[41,[42,[2,0,0,0,0.520833125],[2,0,0,0,0]],[43,[4,4283190348],[0,512,512]],[44],[45],[46],[47,false],[48]]],[22,"Camera",1,[-43],[1,0,0,1000]],[49,0,640,0,1108344832,12,[4,4278190080]],[50,1,10,[[51,"cell",5]]]],0,[0,0,1,0,3,13,0,0,1,0,0,1,0,4,14,0,0,1,0,-1,12,0,-2,6,0,-3,2,0,-4,3,0,-5,5,0,0,2,0,0,2,0,0,2,0,-1,7,0,0,3,0,0,3,0,0,3,0,-1,4,0,0,4,0,0,4,0,0,4,0,-1,8,0,0,5,0,0,5,0,-1,9,0,-2,10,0,0,6,0,0,6,0,0,6,0,0,7,0,0,7,0,0,7,0,0,8,0,0,8,0,0,8,0,0,9,0,0,9,0,0,9,0,0,10,0,0,10,0,-3,14,0,-1,13,0,5,11,1,6,11,43],[0,0,0,0,0,0,0,0,0],[1,1,1,7,1,8,9,10,11],[4,0,0,0,5,1,2,6,1]],[[{"name":"chat_l","rect":{"x":0,"y":0,"width":96,"height":96},"offset":{"x":0,"y":0},"originalSize":{"width":96,"height":96},"rotated":false,"capInsets":[30,30,30,30],"vertices":{"rawPosition":[-48,-48,0,48,-48,0,-48,48,0,48,48,0],"indexes":[0,1,2,2,1,3],"uv":[0,96,96,96,0,0,96,0],"nuv":[0,0,1,0,0,1,1,1],"minPos":{"x":-48,"y":-48,"z":0},"maxPos":{"x":48,"y":48,"z":0}},"packable":true,"pixelsToUnit":100,"pivot":{"x":0.5,"y":0.5},"meshType":0}],[3],0,[0],[2],[7]],[[{"name":"chat_r","rect":{"x":0,"y":0,"width":96,"height":96},"offset":{"x":0,"y":0},"originalSize":{"width":96,"height":96},"rotated":false,"capInsets":[30,30,30,30],"vertices":{"rawPosition":[-48,-48,0,48,-48,0,-48,48,0,48,48,0],"indexes":[0,1,2,2,1,3],"uv":[0,96,96,96,0,0,96,0],"nuv":[0,0,1,0,0,1,1,1],"minPos":{"x":-48,"y":-48,"z":0},"maxPos":{"x":48,"y":48,"z":0}},"packable":true,"pixelsToUnit":100,"pivot":{"x":0.5,"y":0.5},"meshType":0}],[3],0,[0],[2],[8]],[[[52,"chat-cell"],[15,"chat-cell",33554432,[-9,-10],[[3,-2,[0,"1aCAu/eI1F9Kd+52mzr6DN"],[5,300,200]],[53,-8,[0,"b5B5/S/s1H5ZIMroFmPYij"],-7,-6,-5,-4,-3]],[2,"837kegjO1Ho6SktSD1Q2ol",null,null,null,-1,0]],[16,"content",33554432,1,[-12,-13],[[3,-11,[0,"e10bCrAjlB9qx+IDXamz/z"],[5,400,70]]],[2,"7bHyA0eLlH5azHNlot9Mdq",null,null,null,1,0]],[6,"bg",33554432,2,[[[3,-14,[0,"df8qFGiUtK7qucig1ATp79"],[5,400,70]],-15,[28,45,96,96,1,-16,[0,"dcuWid5jFCrb+MtnqdAMA5"]]],4,1,4],[2,"e5tWtyDdBENLJr+LGtqUTL",null,null,null,1,0]],[17,"sender",33554432,1,[-18],[[3,-17,[0,"d4YhVwwKVIM5sS+SsXZ+r4"],[5,70,70]]],[2,"b495Vkiu9GSKErjhE9PTsV",null,null,null,1,0],[1,-100,0,0]],[18,"scale",33554432,4,[-20,-21],[[23,-19,[0,"cdUmr0YB5KV5izq4aJUbDt"]]],[2,"38Cq42WVxJ05f2cnXYyKJ2",null,null,null,1,0],[1,0.6,0.6,1]],[6,"label",33554432,2,[[[3,-22,[0,"01an34IFBGxpCS8Kx1AklC"],[5,63.3837890625,50.4]],-23],4,1],[2,"dfyuYbzK9JiYQ31SRZmxLA",null,null,null,1,0]],[19,"bg",33554432,5,[[3,-24,[0,"21J9SSj3pAnKtdV8WZ+7OC"],[5,106,106]],[32,-25,[0,"99L/6hFLRG+qKuXj9nxfSF"],0]],[2,"dbSXoofM5OHqMwWMXQoJEp",null,null,null,1,0]],[21,"head",33554432,5,[[[3,-26,[0,"b51haCi6RFgoXyrqFMLnfR"],[5,111,96]],-27],4,1],[2,"5cSsKYeY1GOZAagNK+MHgt",null,null,null,1,0],[1,7.895,0,0]],[33,1,0,3,[0,"e75tEP7OpKbJXLNE3OJi+H"],[4,4290815587]],[38,0,30,30,3,6,[0,"f7oBOFpMdKn65/bb0AJwuP"]],[34,8,[0,"aeHIQGLDFIEK34Rc90CjKA"]]],0,[0,12,1,0,0,1,0,13,2,0,14,4,0,15,9,0,16,11,0,17,10,0,0,1,0,-1,2,0,-2,4,0,0,2,0,-1,3,0,-2,6,0,0,3,0,-2,9,0,0,3,0,0,4,0,-1,5,0,0,5,0,-1,7,0,-2,8,0,0,6,0,-2,10,0,0,7,0,0,7,0,0,8,0,-2,11,0,18,1,27],[0,9,11],[1,1,1],[9,2,10]],[[{"name":"chat_bg","rect":{"x":3,"y":9,"width":95,"height":119},"offset":{"x":0.5,"y":-4},"originalSize":{"width":100,"height":129},"rotated":false,"capInsets":[20,40,20,35],"vertices":{"rawPosition":[-47.5,-59.5,0,47.5,-59.5,0,-47.5,59.5,0,47.5,59.5,0],"indexes":[0,1,2,2,1,3],"uv":[3,120,98,120,3,1,98,1],"nuv":[0.03,0.007751937984496124,0.98,0.007751937984496124,0.03,0.9302325581395349,0.98,0.9302325581395349],"minPos":{"x":-47.5,"y":-59.5,"z":0},"maxPos":{"x":47.5,"y":59.5,"z":0}},"packable":true,"pixelsToUnit":100,"pivot":{"x":0.5,"y":0.5},"meshType":0}],[3],0,[0],[2],[11]]]]
